{
  "slug": "taxi-ciovo-skradin",
  "title": "Taksi Čiovo - Skradin | Fiksna cena €115 | TAXI Antonio",
  "description": "Zasebni taksi in prevoz, relacija Čiovo - Skradin. Fiksna cena €115 na vozilo, do 4 potniki, od vrat do vrat. Rezervirajte neposredno pri Antoniu.",
  "keywords": "taksi čiovo - skradin, prevoz čiovo - skradin, letališki prevoz čiovo - skradin",
  "og_image": "https://taxiskradin.hr/assets/img/skradin-hero-city.webp",
  "schema": [
    {
      "@context": "https://schema.org",
      "@type": "Service",
      "serviceType": "Zasebni taksi prevoz",
      "name": "Taksi Čiovo - Skradin",
      "description": "Zasebni taksi in prevoz po fiksni ceni, relacija Čiovo - Skradin, 115 evrov na vozilo za do 4 potnike, od vrat do vrat.",
      "provider": {
        "@type": "LocalBusiness",
        "name": "Taxi Antonio",
        "telephone": "+385994471013",
        "email": "info@taxiskradin.hr",
        "address": {
          "@type": "PostalAddress",
          "addressLocality": "Skradin",
          "addressCountry": "HR"
        },
        "aggregateRating": {
          "@type": "AggregateRating",
          "ratingValue": "4.9",
          "reviewCount": "142"
        }
      },
      "areaServed": [
        "Čiovo",
        "Skradin"
      ],
      "url": "https://taxiskradin.hr/sl/taxi-ciovo-skradin/",
      "offers": {
        "@type": "Offer",
        "price": "115",
        "priceCurrency": "EUR",
        "description": "Enosmerna zasebna vožnja, relacija Čiovo - Skradin, na vozilo za do 4 potnike. Tja in nazaj 230 evrov."
      }
    },
    {
      "@context": "https://schema.org",
      "@type": "FAQPage",
      "mainEntity": [
        {
          "@type": "Question",
          "name": "Koliko stane taksi na relaciji Čiovo - Skradin?",
          "acceptedAnswer": {
            "@type": "Answer",
            "text": "Fiksno 115 na vozilo za do 4 potnike, enosmerna vožnja, prtljaga vključena. Vožnja tja in nazaj stane 230."
          }
        },
        {
          "@type": "Question",
          "name": "Kje me prevzamete?",
          "acceptedAnswer": {
            "@type": "Answer",
            "text": "Na vašem točnem naslovu, naj bo hiša, hotel ali apartma. Pošljite naslov ob rezervaciji in potrdim mesto srečanja."
          }
        },
        {
          "@type": "Question",
          "name": "Kako vnaprej naj rezerviram?",
          "acceptedAnswer": {
            "@type": "Answer",
            "text": "Vsaj 2 uri prej, da lahko potrdim vozilo in čas prevzema. Za vožnjo v zadnjem trenutku pokličite ali pišite na WhatsApp."
          }
        }
      ]
    }
  ]
}