{
  "slug": "",
  "title": "Taksi Skradin | Posjetite Krku | Transferi po fiksnoj cijeni | Taxi Antonio",
  "description": "Taksi Skradin za lokalne vožnje, brodsko pristanište Nacionalnog parka Krka, ACI Marinu Skradin i transfere do zračnih luka po fiksnoj cijeni. Vozač govori engleski. Rezervirajte izravno kod Antonija.",
  "keywords": "taxi skradin, taksi skradin, transfer skradin, transfer zračna luka skradin, taksi skradin krka, taksi aci marina skradin, taksi nacionalni park krka",
  "og_image": "https://taxiskradin.hr/assets/img/hero-bg.webp",
  "schema": [
    {
      "@context": "https://schema.org",
      "@type": "LocalBusiness",
      "name": "TAXI Skradin - Antonio",
      "url": "https://taxiskradin.hr/",
      "telephone": "+385994471013",
      "email": "info@taxiskradin.hr",
      "areaServed": [
        "Skradin",
        "Nacionalni park Krka",
        "ACI Marina Skradin",
        "Šibenik",
        "Split",
        "Zadar",
        "Dubrovnik",
        "Zagreb"
      ],
      "address": {
        "@type": "PostalAddress",
        "addressLocality": "Skradin",
        "postalCode": "22222",
        "addressCountry": "HR"
      },
      "aggregateRating": {
        "@type": "AggregateRating",
        "ratingValue": "4.9",
        "reviewCount": "142"
      },
      "priceRange": "€€",
      "alternateName": "TAXI Antonio",
      "@id": "https://taxiskradin.hr/#business",
      "image": "https://taxiskradin.hr/assets/img/hero-bg.webp",
      "paymentAccepted": "Gotovina, kreditna kartica",
      "currenciesAccepted": "EUR",
      "geo": {
        "@type": "GeoCoordinates",
        "latitude": 43.8186,
        "longitude": 15.9214
      },
      "hasMap": "https://www.google.com/maps?cid=4748268601430744277",
      "openingHoursSpecification": [
        {
          "@type": "OpeningHoursSpecification",
          "dayOfWeek": [
            "Monday",
            "Tuesday",
            "Wednesday",
            "Thursday",
            "Friday"
          ],
          "opens": "07:00",
          "closes": "14:00"
        },
        {
          "@type": "OpeningHoursSpecification",
          "dayOfWeek": [
            "Monday",
            "Tuesday",
            "Wednesday",
            "Thursday",
            "Friday"
          ],
          "opens": "16:00",
          "closes": "21:00"
        },
        {
          "@type": "OpeningHoursSpecification",
          "dayOfWeek": [
            "Saturday",
            "Sunday"
          ],
          "opens": "06:00",
          "closes": "16:00"
        }
      ],
      "sameAs": [
        "https://web.facebook.com/profile.php?id=61579783829997",
        "https://www.instagram.com/taxi_sibenik/",
        "https://www.tiktok.com/@taxisibenik",
        "https://www.tripadvisor.com/Attraction_Review-g295375-d24821165-Reviews-TAXI_Sibenik_Skradin_Antonio-Sibenik_Sibenik_Knin_County_Dalmatia.html",
        "https://www.google.com/maps?cid=4748268601430744277"
      ]
    },
    {
      "@context": "https://schema.org",
      "@type": "Service",
      "serviceType": "Taksi i transfer usluga",
      "name": "Taksi Skradin od TAXI Antonio",
      "areaServed": {
        "@type": "City",
        "name": "Skradin"
      },
      "provider": {
        "@type": "LocalBusiness",
        "name": "Taxi Antonio",
        "telephone": "+385994471013",
        "aggregateRating": {
          "@type": "AggregateRating",
          "ratingValue": "4.9",
          "reviewCount": "142"
        }
      },
      "hasOfferCatalog": {
        "@type": "OfferCatalog",
        "name": "Taksi i transfer usluge",
        "itemListElement": [
          {
            "@type": "Offer",
            "itemOffered": {
              "@type": "Service",
              "name": "Lokalne taksi vožnje u Skradinu"
            }
          },
          {
            "@type": "Offer",
            "itemOffered": {
              "@type": "Service",
              "name": "Transferi do brodskog pristaništa Nacionalnog parka Krka"
            }
          },
          {
            "@type": "Offer",
            "itemOffered": {
              "@type": "Service",
              "name": "Transferi iz i do ACI Marine Skradin"
            }
          },
          {
            "@type": "Offer",
            "itemOffered": {
              "@type": "Service",
              "name": "Transferi do zračnih luka"
            }
          },
          {
            "@type": "Offer",
            "itemOffered": {
              "@type": "Service",
              "name": "Međugradski transferi"
            }
          }
        ]
      }
    },
    {
      "@context": "https://schema.org",
      "@type": "FAQPage",
      "mainEntity": [
        {
          "@type": "Question",
          "name": "Kako rezerviram taksi u Skradinu?",
          "acceptedAnswer": {
            "@type": "Answer",
            "text": "Nazovite +385 99 447 1013, javite se na WhatsApp ili pošaljite e-mail. Antoniju trebaju mjesto preuzimanja, odredište i željeno vrijeme preuzimanja ili dolaska."
          }
        },
        {
          "@type": "Question",
          "name": "Koliko unaprijed trebam rezervirati?",
          "acceptedAnswer": {
            "@type": "Answer",
            "text": "Zahtjevi u zadnji čas prihvaćaju se unutar radnog vremena, ali rezervacija traži najmanje 2 sata unaprijed kako bi se potvrdili vozilo i vrijeme preuzimanja. Ranija rezervacija jamči dostupnost."
          }
        },
        {
          "@type": "Question",
          "name": "Što znači \"fiksna cijena\"? Što je uključeno?",
          "acceptedAnswer": {
            "@type": "Answer",
            "text": "Fiksne cijene uključuju prijevoz, gorivo, cestarine i pomoć s prtljagom. Bez skrivenih troškova. Dodatna stajanja ili duže čekanje mogu koštati više, o čemu se javlja unaprijed."
          }
        },
        {
          "@type": "Question",
          "name": "Naplaćujete li predujam?",
          "acceptedAnswer": {
            "@type": "Answer",
            "text": "Da. Potvrda rezervacije traži predujam od 20% (najmanje 20 eura). Vožnje s cijenom od 20 eura ili manje plaćaju se u cijelosti unaprijed. Predujam se može platiti bankovnim prijenosom (SEPA) ili karticom, a ostatak se podmiruje na dan vožnje, gotovinom ili karticom."
          }
        },
        {
          "@type": "Question",
          "name": "Prihvaćate li plaćanje karticom u vozilu?",
          "acceptedAnswer": {
            "@type": "Answer",
            "text": "Da, prihvaćaju se kartice i drugi beskontaktni načini plaćanja."
          }
        },
        {
          "@type": "Question",
          "name": "Možete li me odvesti do ulaza u Nacionalni park Krka u Skradinu?",
          "acceptedAnswer": {
            "@type": "Answer",
            "text": "Da. Skradin je glavni ulaz u Krku. Antonio vas ostavlja na pristaništu uz rivu odakle brodovi parka polaze prema slapovima Skradinski buk i dolazi po vas kad se vratite."
          }
        },
        {
          "@type": "Question",
          "name": "Preuzimate li goste u ACI Marini Skradin?",
          "acceptedAnswer": {
            "@type": "Answer",
            "text": "Da. Antonio preuzima i dovozi posade točno u ACI Marinu Skradin, s prostorom za prtljagu i namirnice. Pošaljite broj veza kako biste dogovorili mjesto susreta."
          }
        },
        {
          "@type": "Question",
          "name": "Vozite li do Šibenika i zračnih luka?",
          "acceptedAnswer": {
            "@type": "Answer",
            "text": "Da. Antonio vozi transfere po fiksnoj cijeni iz Skradina do Šibenika, zračnih luka Split i Zadar te gradova diljem Dalmacije. Za vožnje koje počinju u samom Šibeniku pogledajte sestrinsku uslugu na taxisibenik.hr."
          }
        },
        {
          "@type": "Question",
          "name": "Što ako mi let kasni?",
          "acceptedAnswer": {
            "@type": "Answer",
            "text": "Dolasci letova prate se u stvarnom vremenu i vrijeme preuzimanja prilagođava se automatski, bez dodatnog troška."
          }
        },
        {
          "@type": "Question",
          "name": "Što ako moram otkazati?",
          "acceptedAnswer": {
            "@type": "Answer",
            "text": "Otkazivanja se moraju napraviti pisanim putem e-mailom. Više od 72 sata prije rezervacije vrijedi puni povrat za bankovni prijenos ili puni povrat umanjen za 10 eura troška obrade za kartično plaćanje. Otkazivanja unutar 72 sata ili nedolazak ne vraćaju se. Promjena termina besplatna je u svakom trenutku."
          }
        },
        {
          "@type": "Question",
          "name": "Možete li primiti veću grupu?",
          "acceptedAnswer": {
            "@type": "Answer",
            "text": "Škoda Superb prima do 4 putnika. Za veće grupe vožnja se može dogovoriti preko lokalnih, pomno odabranih partnera."
          }
        },
        {
          "@type": "Question",
          "name": "Nudite li dječje sjedalice?",
          "acceptedAnswer": {
            "@type": "Answer",
            "text": "Da, dječje sjedalice i podsjedači dostupni su na zahtjev."
          }
        }
      ]
    }
  ]
}
